gbp_webhook_playsound-1.0.1.dist-info/METADATA
gbp_webhook_playsound-1.0.1.dist-info/WHEEL
gbp_webhook_playsound-1.0.1.dist-info/entry_points.txt
gbp_webhook_playsound-1.0.1.dist-info/licenses/LICENSE
gbp_webhook_playsound/__init__.py
gbp_webhook_playsound/handlers.py
gbp_webhook_playsound/level-up-191997.mp3
gbp_webhook_playsound/py.typed
gbp_webhook_playsound-1.0.1.dist-info/RECORD
