Metadata-Version: 2.1
Name: gbp-webhook-playsound
Version: 1.0.1
Summary: gbp-webhook to play a sound when a build is pulled
Author-Email: Albert Hopkins <marduk@letterboxes.org>
License: GPL3+
Project-URL: homepage, https://github.com/enku/gbp-webhook-playsound
Project-URL: repository, https://github.com/enku/gbp-webhook-playsound
Requires-Python: >=3.12
